pyfly/__init__.py
pyfly/dryden.py
pyfly/pid_controller.py
pyfly/pyfly.py
pyfly/pyfly_config.json
pyfly/x8_param.mat
pyfly_fixed_wing-0.1.2.dist-info/LICENSE
pyfly_fixed_wing-0.1.2.dist-info/METADATA
pyfly_fixed_wing-0.1.2.dist-info/WHEEL
pyfly_fixed_wing-0.1.2.dist-info/top_level.txt
pyfly_fixed_wing-0.1.2.dist-info/RECORD
