Metadata-Version: 2.1
Name: pyfly-fixed-wing
Version: 0.1.2
Summary: Python Fixed-Wing Flight Simulator
Home-page: https://github.com/eivindeb/pyfly
Author: Eivind Bøhn
Author-email: eivind.bohn@gmail.com
License: MIT
Platform: UNKNOWN
Requires-Dist: cycler (>=0.10.0)
Requires-Dist: kiwisolver (>=1.1.0)
Requires-Dist: matplotlib (>=3.1.0)
Requires-Dist: numpy (>=1.16.4)
Requires-Dist: pyparsing (>=2.4.0)
Requires-Dist: python-dateutil (>=2.8.0)
Requires-Dist: scipy (>=1.3.0)
Requires-Dist: six (>=1.12.0)
